goosebit/__init__.py
goosebit/__main__.py
goosebit/api/__init__.py
goosebit/api/responses.py
goosebit/api/routes.py
goosebit/api/telemetry/__init__.py
goosebit/api/telemetry/metrics.py
goosebit/api/telemetry/prometheus/__init__.py
goosebit/api/telemetry/prometheus/readers.py
goosebit/api/telemetry/prometheus/routes.py
goosebit/api/telemetry/routes.py
goosebit/api/v1/__init__.py
goosebit/api/v1/devices/__init__.py
goosebit/api/v1/devices/device/__init__.py
goosebit/api/v1/devices/device/responses.py
goosebit/api/v1/devices/device/routes.py
goosebit/api/v1/devices/requests.py
goosebit/api/v1/devices/responses.py
goosebit/api/v1/devices/routes.py
goosebit/api/v1/download/__init__.py
goosebit/api/v1/download/routes.py
goosebit/api/v1/rollouts/__init__.py
goosebit/api/v1/rollouts/requests.py
goosebit/api/v1/rollouts/responses.py
goosebit/api/v1/rollouts/routes.py
goosebit/api/v1/routes.py
goosebit/api/v1/settings/__init__.py
goosebit/api/v1/settings/routes.py
goosebit/api/v1/settings/users/__init__.py
goosebit/api/v1/settings/users/requests.py
goosebit/api/v1/settings/users/responses.py
goosebit/api/v1/settings/users/routes.py
goosebit/api/v1/software/__init__.py
goosebit/api/v1/software/requests.py
goosebit/api/v1/software/responses.py
goosebit/api/v1/software/routes.py
goosebit/auth/__init__.py
goosebit/auth/permissions.py
goosebit/db/__init__.py
goosebit/db/config.py
goosebit/db/migrations/models/0_20240830054046_init.py
goosebit/db/migrations/models/1_20241109151811_update.py
goosebit/db/migrations/models/2_20241121113728_update.py
goosebit/db/migrations/models/3_20241121140210_update.py
goosebit/db/migrations/models/4_20250324110331_update.py
goosebit/db/migrations/models/4_20250402085235_rename_uuid_to_id.py
goosebit/db/migrations/models/5_20250619090242_null_feed.py
goosebit/db/migrations/models/6_20250904081506_add_image_format.py
goosebit/db/models.py
goosebit/db/pg_ssl_context.py
goosebit/device_manager.py
goosebit/plugins/__init__.py
goosebit-0.2.11.dist-info/METADATA
goosebit-0.2.11.dist-info/WHEEL
goosebit-0.2.11.dist-info/entry_points.txt
goosebit-0.2.11.dist-info/licenses/LICENSE
goosebit-0.2.11.dist-info/RECORD
