Metadata-Version: 2.4
Name: goosebit
Version: 0.2.11
Summary: A simplistic, opinionated remote update server implementing hawkBit™'s DDI API
License-File: LICENSE
Author: Brett Rowan
Author-email: 121075405+b-rowan@users.noreply.github.com
Requires-Python: >=3.11,<4.0
Classifier: Programming Language :: Python :: 3
Classifier: Programming Language :: Python :: 3.11
Classifier: Programming Language :: Python :: 3.12
Classifier: Programming Language :: Python :: 3.13
Classifier: Programming Language :: Python :: 3.14
Provides-Extra: postgresql
Requires-Dist: aerich (>=0.9.1,<0.10.0)
Requires-Dist: aiocache (>=0.12.3,<0.13.0)
Requires-Dist: argon2-cffi (>=25.1.0,<26.0.0)
Requires-Dist: asyncpg (>=0.30.0,<0.31.0) ; extra == "postgresql"
Requires-Dist: boto3 (>=1.40.8,<2.0.0)
Requires-Dist: fastapi (>=0.116.1,<0.118.0)
Requires-Dist: httpx (>=0.28.1,<0.29.0)
Requires-Dist: itsdangerous (>=2.2.0,<3.0.0)
Requires-Dist: jinja2 (>=3.1.6,<4.0.0)
Requires-Dist: joserfc (>=1.2.2,<2.0.0)
Requires-Dist: libconf (>=2.0.1,<3.0.0)
Requires-Dist: opentelemetry-distro (>=0.57b0,<0.59)
Requires-Dist: opentelemetry-exporter-prometheus (>=0.57b0,<0.59)
Requires-Dist: opentelemetry-instrumentation-fastapi (>=0.57b0,<0.59)
Requires-Dist: pydantic-settings[yaml] (>=2.10.1,<3.0.0)
Requires-Dist: pysquashfsimage (>=0.9.0,<1.0.0)
Requires-Dist: python-multipart (>=0.0.20,<0.0.21)
Requires-Dist: semver (>=3.0.4,<4.0.0)
Requires-Dist: tortoise-orm (>=0.25.1,<0.26.0)
Requires-Dist: uvicorn (>=0.35.0,<0.37.0)
Requires-Dist: zstandard (>=0.24.0,<0.26.0)
